[{"id": 1960, "text": "So the first thing is something that makes me angry.", "time": 19600000, "duration": 2910.0, "language": "en"}, {"id": 8460, "text": "I feel like there's some.", "time": 84600000, "duration": 1470.0, "language": "en"}, {"id": 11220, "text": "Teachers GIX.", "time": 112200000, "duration": 2970.0, "language": "en"}, {"id": 19270, "text": "I don't dislike them, but I think sometimes they can act very childish like they're so sensitive and they get this like.", "time": 192700000, "duration": 8510.0, "language": "en"}, {"id": 32510, "text": "Yeah, they just act like children, sometimes like today or no no few few weeks ago.", "time": 325100000, "duration": 7810.0, "language": "en"}, {"id": 40970, "text": "I some of the teachers.", "time": 409700000, "duration": 2410.0, "language": "en"}, {"id": 43930, "text": "They sound like an email is very confusing to people or something. So I forget what the issue is, but like some scheduling problem. So I told him I explained to him and I didn't think I was aggressive, I was like happy.", "time": 439300000, "duration": 14740.0, "language": "en"}, {"id": 59800, "text": "But he got very like.", "time": 598000000, "duration": 1420.0, "language": "en"}, {"id": 62850, "text": "Uh just passive aggressive, I mean, just like.", "time": 628500000, "duration": 4430.0, "language": "en"}, {"id": 68230, "text": "Kind of like not very happy with me, but not really showing it an.", "time": 682300000, "duration": 4130.0, "language": "en"}, {"id": 73830, "text": "And we were like talking about.", "time": 738300000, "duration": 2260.0, "language": "en"}, {"id": 76810, "text": "Whose interpretation of something of some communication is right, and the teacher brought it to another teacher is like no no my interpretation is right, you brought it to another teacher and the other teacher more agreed with me and then that teacher got really upset and he was like Oh, you should be a lawyer.", "time": 768100000, "duration": 16290.0, "language": "en"}, {"id": 93650, "text": "So these kind of things like so childish.", "time": 936500000, "duration": 2430.0, "language": "en"}, {"id": 96990, "text": "It's just like I feel one thing I learned in this program is adults are.", "time": 969900000, "duration": 6350.0, "language": "en"}, {"id": 104570, "text": "Doesn't mean they're mature just because you're older it doesn't really mean you're like? Yeah, you can still not escape.", "time": 1045700000, "duration": 9170.0, "language": "en"}, {"id": 115180, "text": "Your bad habits from when you're a kid.", "time": 1151800000, "duration": 2190.0, "language": "en"}, {"id": 120520, "text": "Anyway, as angry stop OK.", "time": 1205200000, "duration": 3610.0, "language": "en"}, 1309]